LICENSE
setup.cfg
setup.py
tiger_krd/V12.py
tiger_krd/__init__.py
tiger_krd.egg-info/PKG-INFO
tiger_krd.egg-info/SOURCES.txt
tiger_krd.egg-info/dependency_links.txt
tiger_krd.egg-info/requires.txt
tiger_krd.egg-info/top_level.txt